wilson/__init__.py
wilson/_version.py
wilson/classes.py
wilson/parameters.py
wilson/test_wilson.py
wilson/data/flavio_jms_lfv.json
wilson/data/flavio_jms_nunull.json
wilson/data/flavio_jms_vii.json
wilson/data/flavorkit_jms.json
wilson/data/flavorkit_jms_conj.json
wilson/data/run_wet_definitions_coeffs.json
wilson/data/tests/wcxf-flavio-example.yml
wilson/match/__init__.py
wilson/match/_smeft_old.py
wilson/match/smeft.py
wilson/match/smeft_loop.py
wilson/match/smeft_tree.py
wilson/match/test_smeft_loop.py
wilson/match/test_smeft_tree_new.py
wilson/match/test_smeft_wet.py
wilson/match/test_symmetryfactors.py
wilson/match/test_wet.py
wilson/run/__init__.py
wilson/run/smeft/__init__.py
wilson/run/smeft/beta.py
wilson/run/smeft/classes.py
wilson/run/smeft/rge.py
wilson/run/smeft/smpar.py
wilson/run/smeft/tests/data/Output_SMEFTrunner.dat
wilson/run/smeft/tests/data/SMInput-CPV.dat
wilson/run/smeft/tests/data/WCsInput-CPV-SMEFT.dat
wilson/run/smeft/tests/data/betas_im.json
wilson/run/smeft/tests/data/betas_re.json
wilson/run/smeft/tests/data/random_par.json
wilson/run/smeft/tests/data/random_wc.json
wilson/run/wet/__init__.py
wilson/run/wet/adm.py
wilson/run/wet/classes.py
wilson/run/wet/definitions.py
wilson/run/wet/rge.py
wilson/run/wet/test_wetrunner.py
wilson/translate/__init__.py
wilson/translate/smeft.py
wilson/translate/smeft_higgs.py
wilson/translate/smeft_smeftsim.py
wilson/translate/smeft_smeftsim_data.py
wilson/translate/test_smeft.py
wilson/translate/test_smeft_higgs.py
wilson/translate/test_smeft_smeftsim.py
wilson/translate/test_wet.py
wilson/translate/wet.py
wilson/util/__init__.py
wilson/util/common.py
wilson/util/qcd.py
wilson/util/smeft_warsaw.py
wilson/util/test_qcd.py
wilson/util/test_smeftutil.py
wilson/util/test_wetutil.py
wilson/util/wet_jms.py
wilson/wcxf/__init__.py
wilson/wcxf/classes.py
wilson/wcxf/cli.py
wilson/wcxf/test_bases.py
wilson/wcxf/test_cli.py
wilson/wcxf/test_smeft.py
wilson/wcxf/test_wcxf.py
wilson/wcxf/test_wet.py
wilson-2.5.2.dist-info/licenses/LICENSE
wilson-2.5.2.dist-info/METADATA
wilson-2.5.2.dist-info/WHEEL
wilson-2.5.2.dist-info/entry_points.txt
wilson-2.5.2.dist-info/top_level.txt
wilson-2.5.2.dist-info/RECORD
