Metadata-Version: 2.4
Name: wilson
Version: 2.5.2
Summary: Toolkit for effective field theories beyond the Standard Model
Home-page: https://github.com/wilson-eft/wilson
Author: Jason Aebischer, David M. Straub
Author-email: jason.aebischer@tum.de, straub@protonmail.com
License: MIT
Requires-Python: >=3.6
License-File: LICENSE
Requires-Dist: numpy>=1.16.5
Requires-Dist: scipy>=1.0
Requires-Dist: pandas
Requires-Dist: pylha>=0.2
Requires-Dist: pyyaml
Requires-Dist: ckmutil>=1.2.0
Requires-Dist: rundec>=0.5
Requires-Dist: voluptuous
Provides-Extra: testing
Requires-Dist: nose; extra == "testing"
Dynamic: author
Dynamic: author-email
Dynamic: description
Dynamic: description-content-type
Dynamic: home-page
Dynamic: license
Dynamic: license-file
Dynamic: provides-extra
Dynamic: requires-dist
Dynamic: requires-python
Dynamic: summary
